loganary/__init__.py
loganary/ranking/__init__.py
loganary/ranking/__version__.py
loganary/ranking/common.py
loganary/ranking/data.py
loganary/ranking/model.py
loganary/ranking/predict.py
loganary/ranking/reader.py
loganary/ranking/fess/__init__.py
loganary/ranking/fess/reader.py
loganary_ranking-0.2.0.dist-info/LICENSE
loganary_ranking-0.2.0.dist-info/METADATA
loganary_ranking-0.2.0.dist-info/WHEEL
loganary_ranking-0.2.0.dist-info/top_level.txt
loganary_ranking-0.2.0.dist-info/RECORD
